tf_kan_latest-1.1.0.dist-info/licenses/LICENSE
tfkan/__init__.py
tfkan/layers/__init__.py
tfkan/layers/base.py
tfkan/layers/convolution.py
tfkan/layers/dense.py
tfkan/ops/__init__.py
tfkan/ops/grid.py
tfkan/ops/spline.py
tf_kan_latest-1.1.0.dist-info/METADATA
tf_kan_latest-1.1.0.dist-info/WHEEL
tf_kan_latest-1.1.0.dist-info/top_level.txt
tf_kan_latest-1.1.0.dist-info/RECORD
