Metadata-Version: 2.4
Name: tf-kan-latest
Version: 1.1.0
Summary: A Keras-native implementation of Kolmogorov-Arnold Networks (KANs) for TensorFlow.
Home-page: https://github.com/sathyasubrahmanya/tf-kan
Author: Sathyasubrahmanya v S
Author-email: sathyapel0005@gmail.com
Keywords: tensorflow,keras,kan,kolmogorov-arnold,neural-networks,machine-learning
Classifier: Programming Language :: Python :: 3
Classifier: Programming Language :: Python :: 3.8
Classifier: Programming Language :: Python :: 3.9
Classifier: Programming Language :: Python :: 3.10
Classifier: Programming Language :: Python :: 3.11
Classifier: Programming Language :: Python :: 3.12
Classifier: License :: OSI Approved :: MIT License
Classifier: Operating System :: OS Independent
Classifier: Intended Audience :: Developers
Classifier: Intended Audience :: Science/Research
Classifier: Topic :: Scientific/Engineering :: Artificial Intelligence
Requires-Python: >=3.8
License-File: LICENSE
Requires-Dist: tensorflow>=2.16.0
Requires-Dist: numpy>=1.23.0
Dynamic: author
Dynamic: author-email
Dynamic: classifier
Dynamic: description
Dynamic: description-content-type
Dynamic: home-page
Dynamic: keywords
Dynamic: license-file
Dynamic: requires-dist
Dynamic: requires-python
Dynamic: summary
